uneq/__init__.py
uneq/cli.py
uneq/uneq.py
uneq-0.1.10.dist-info/METADATA
uneq-0.1.10.dist-info/WHEEL
uneq-0.1.10.dist-info/entry_points.txt
uneq-0.1.10.dist-info/RECORD
